rctogether/__init__.py
rctogether/api.py
rctogether/bots.py
rctogether/messages.py
rctogether/notes.py
rctogether/walls.py
rctogether/websocket_subscription.py
rctogether-0.3.4.dist-info/METADATA
rctogether-0.3.4.dist-info/WHEEL
rctogether-0.3.4.dist-info/licenses/LICENSE
rctogether-0.3.4.dist-info/RECORD
